[
  {
    "name": "stellaswap-stella-avax",
    "address": "0x2AB268c6025F7Cd76A4B6a8A5bc7fE780Fbbfe98",
    "decimals": "1e18",
    "poolId": 9,
    "chainId": 1284,
    "lp0": {
      "address": "0x0E358838ce72d5e61E0018a2ffaC4bEC5F4c88d2",
      "oracle": "tokens",
      "oracleId": "STELLA",
      "decimals": "1e18"
    },
    "lp1": {
      "address": "0x4792C1EcB969B036eb51330c63bD27899A13D84e",
      "oracle": "tokens",
      "oracleId": "AVAX",
      "decimals": "1e18"
    }
  },
  {
    "name": "stellaswap-busd-wglmr",
    "address": "0x367c36dAE9ba198A4FEe295c22bC98cB72f77Fe1",
    "decimals": "1e18",
    "poolId": 8,
    "chainId": 1284,
    "lp0": {
      "address": "0xA649325Aa7C5093d12D6F98EB4378deAe68CE23F",
      "oracle": "tokens",
      "oracleId": "BUSD",
      "decimals": "1e18"
    },
    "lp1": {
      "address": "0xAcc15dC74880C9944775448304B263D191c6077F",
      "oracle": "tokens",
      "oracleId": "WGLMR",
      "decimals": "1e18"
    }
  },
  {
    "name": "stellaswap-wglmr-eth",
    "address": "0x49a1cC58dCf28D0139dAEa9c18A3ca23108E78B3",
    "decimals": "1e18",
    "poolId": 7,
    "chainId": 1284,
    "lp0": {
      "address": "0xAcc15dC74880C9944775448304B263D191c6077F",
      "oracle": "tokens",
      "oracleId": "WGLMR",
      "decimals": "1e18"
    },
    "lp1": {
      "address": "0xfA9343C3897324496A05fC75abeD6bAC29f8A40f",
      "oracle": "tokens",
      "oracleId": "ETH",
      "decimals": "1e18"
    }
  },
  {
    "name": "stellaswap-stella-usdc",
    "address": "0x81e11a9374033d11Cc7e7485A7192AE37D0795D6",
    "decimals": "1e18",
    "poolId": 6,
    "chainId": 1284,
    "lp0": {
      "address": "0x0E358838ce72d5e61E0018a2ffaC4bEC5F4c88d2",
      "oracle": "tokens",
      "oracleId": "STELLA",
      "decimals": "1e18"
    },
    "lp1": {
      "address": "0x818ec0A7Fe18Ff94269904fCED6AE3DaE6d6dC0b",
      "oracle": "tokens",
      "oracleId": "USDC",
      "decimals": "1e6"
    }
  },
  {
    "name": "stellaswap-usdc-wglmr",
    "address": "0x555B74dAFC4Ef3A5A1640041e3244460Dc7610d1",
    "decimals": "1e18",
    "poolId": 5,
    "chainId": 1284,
    "lp0": {
      "address": "0x818ec0a7fe18ff94269904fced6ae3dae6d6dc0b",
      "oracle": "tokens",
      "oracleId": "USDC",
      "decimals": "1e6"
    },
    "lp1": {
      "address": "0xAcc15dC74880C9944775448304B263D191c6077F",
      "oracle": "tokens",
      "oracleId": "WGLMR",
      "decimals": "1e18"
    }
  },
  {
    "name": "stellaswap-usdc-bnb",
    "address": "0xAc2657ba28768FE5F09052f07A9B7ea867A4608f",
    "decimals": "1e18",
    "poolId": 4,
    "chainId": 1284,
    "lp0": {
      "address": "0x818ec0A7Fe18Ff94269904fCED6AE3DaE6d6dC0b",
      "oracle": "tokens",
      "oracleId": "USDC",
      "decimals": "1e6"
    },
    "lp1": {
      "address": "0xc9BAA8cfdDe8E328787E29b4B078abf2DaDc2055",
      "oracle": "tokens",
      "oracleId": "BNB",
      "decimals": "1e18"
    }
  },
  {
    "name": "stellaswap-dai-usdc",
    "address": "0x5Ced2f8DD70dc25cbA10ad18c7543Ad9ad5AEeDD",
    "decimals": "1e18",
    "poolId": 3,
    "chainId": 1284,
    "lp0": {
      "address": "0x765277eebeca2e31912c9946eae1021199b39c61",
      "oracle": "tokens",
      "oracleId": "DAI",
      "decimals": "1e18"
    },
    "lp1": {
      "address": "0x818ec0a7fe18ff94269904fced6ae3dae6d6dc0b",
      "oracle": "tokens",
      "oracleId": "USDC",
      "decimals": "1e6"
    }
  },
  {
    "name": "stellaswap-usdc-usdt",
    "address": "0x8BC3CceeF43392B315dDD92ba30b435F79b66b9e",
    "decimals": "1e18",
    "poolId": 2,
    "chainId": 1284,
    "lp0": {
      "address": "0x818ec0A7Fe18Ff94269904fCED6AE3DaE6d6dC0b",
      "oracle": "tokens",
      "oracleId": "USDC",
      "decimals": "1e6"
    },
    "lp1": {
      "address": "0xeFAeeE334F0Fd1712f9a8cc375f427D9Cdd40d73",
      "oracle": "tokens",
      "oracleId": "USDT",
      "decimals": "1e6"
    }
  },
  {
    "name": "stellaswap-stella-wglmr",
    "address": "0x7F5Ac0FC127bcf1eAf54E3cd01b00300a0861a62",
    "decimals": "1e18",
    "poolId": 0,
    "chainId": 1284,
    "lp0": {
      "address": "0x0e358838ce72d5e61e0018a2ffac4bec5f4c88d2",
      "oracle": "tokens",
      "oracleId": "STELLA",
      "decimals": "1e18"
    },
    "lp1": {
      "address": "0xacc15dc74880c9944775448304b263d191c6077f",
      "oracle": "tokens",
      "oracleId": "WGLMR",
      "decimals": "1e18"
    }
  }
]


