[
  {
    "name": "tndr-tndr-busd",
    "address": "0x3d63B28ea380d6948b4A8d65E30Cb4ECe478abbA",
    "decimals": "1e18",
    "poolId": 1,
    "chainId": 56,
    "lp0": {
      "address": "0x7Cc46141AB1057b1928de5Ad5Ee78Bb37eFC4868",
      "oracle": "tokens",
      "oracleId": "TNDR",
      "decimals": "1e18"
    },
    "lp1": {
      "address": "0xe9e7CEA3DedcA5984780Bafc599bD69ADd087D56",
      "oracle": "tokens",
      "oracleId": "BUSD",
      "decimals": "1e18"
    }
  },
  {
    "name": "tndr-tndr-bnb",
    "address": "0xE3652C5F32B0EbCa4A7752269837d110fbdCfC06",
    "decimals": "1e18",
    "poolId": 2,
    "chainId": 56,
    "lp0": {
      "address": "0x7Cc46141AB1057b1928de5Ad5Ee78Bb37eFC4868",
      "oracle": "tokens",
      "oracleId": "TNDR",
      "decimals": "1e18"
    },
    "lp1": {
      "address": "0xbb4CdB9CBd36B01bD1cBaEBF2De08d9173bc095c",
      "oracle": "tokens",
      "oracleId": "WBNB",
      "decimals": "1e18"
    }
  }
]
