[
  {
    "name": "street-btri-bnb",
    "address": "0x982eE1343c73688314990483dea924808231dE4D",
    "poolId": 30,
    "decimals": "1e18",
    "lp0": {
      "address": "0x30C18C9cb3de61f2BD1974749A6f5725150208F3",
      "oracle": "pancake",
      "oracleId": "bTRI",
      "decimals": "1e9"
    },
    "lp1": {
      "address": "0xbb4CdB9CBd36B01bD1cBaEBF2De08d9173bc095c",
      "oracle": "pancake",
      "oracleId": "WBNB",
      "decimals": "1e18"
    }
  },
  {
    "name": "street-btri-cred",
    "address": "0xF271F9Cc3E3626394978A9C0C9582931fa3caDD1",
    "poolId": 31,
    "decimals": "1e18",
    "lp0": {
      "address": "0x30C18C9cb3de61f2BD1974749A6f5725150208F3",
      "oracle": "pancake",
      "oracleId": "bTRI",
      "decimals": "1e9"
    },
    "lp1": {
      "address": "0x571D0B55fe30eb1F6E68e8799F181c46De6B0059",
      "oracle": "pancake",
      "oracleId": "CRED",
      "decimals": "1e18"
    }
  },
  {
    "name": "street-bhc-bnb",
    "address": "0xd46E7f33f8788f87D6017074dC4e4d781D3df91E",
    "poolId": 28,
    "decimals": "1e18",
    "lp0": {
      "address": "0x6fd7c98458a943f469E1Cf4eA85B173f5Cd342F4",
      "oracle": "pancake",
      "oracleId": "BHC",
      "decimals": "1e18"
    },
    "lp1": {
      "address": "0xbb4CdB9CBd36B01bD1cBaEBF2De08d9173bc095c",
      "oracle": "pancake",
      "oracleId": "WBNB",
      "decimals": "1e18"
    }
  },
  {
    "name": "street-jgn-bnb",
    "address": "0xc7C4726D0A45E4e7392901A90dCB52Ec4d2Bd1a3",
    "poolId": 29,
    "decimals": "1e18",
    "lp0": {
      "address": "0xC13B7a43223BB9Bf4B69BD68Ab20ca1B79d81C75",
      "oracle": "pancake",
      "oracleId": "JGN",
      "decimals": "1e18"
    },
    "lp1": {
      "address": "0xbb4CdB9CBd36B01bD1cBaEBF2De08d9173bc095c",
      "oracle": "pancake",
      "oracleId": "WBNB",
      "decimals": "1e18"
    }
  },
  {
    "name": "street-twt-bnb",
    "address": "0xf7f21A56B19546A77EABABf23d8dca726CaF7577",
    "poolId": 22,
    "decimals": "1e18",
    "lp0": {
      "address": "0x4B0F1812e5Df2A09796481Ff14017e6005508003",
      "oracle": "pancake",
      "oracleId": "TWT",
      "decimals": "1e18"
    },
    "lp1": {
      "address": "0xbb4CdB9CBd36B01bD1cBaEBF2De08d9173bc095c",
      "oracle": "pancake",
      "oracleId": "WBNB",
      "decimals": "1e18"
    }
  },
  {
    "name": "street-sxp-bnb",
    "address": "0xf08865069864A5a62EB4DD4b9dcB66834822a198",
    "poolId": 23,
    "decimals": "1e18",
    "lp0": {
      "address": "0x47BEAd2563dCBf3bF2c9407fEa4dC236fAbA485A",
      "oracle": "pancake",
      "oracleId": "SXP",
      "decimals": "1e18"
    },
    "lp1": {
      "address": "0xbb4CdB9CBd36B01bD1cBaEBF2De08d9173bc095c",
      "oracle": "pancake",
      "oracleId": "WBNB",
      "decimals": "1e18"
    }
  },
  {
    "name": "street-xvs-bnb",
    "address": "0x52a7FBe0995607B74e77A367036E76BCE11A3B44",
    "poolId": 24,
    "decimals": "1e18",
    "lp0": {
      "address": "0xcF6BB5389c92Bdda8a3747Ddb454cB7a64626C63",
      "oracle": "pancake",
      "oracleId": "XVS",
      "decimals": "1e18"
    },
    "lp1": {
      "address": "0xbb4CdB9CBd36B01bD1cBaEBF2De08d9173bc095c",
      "oracle": "pancake",
      "oracleId": "WBNB",
      "decimals": "1e18"
    }
  },
  {
    "name": "street-inj-bnb",
    "address": "0x45ac15fb9650a790A0cD0f2b10c5EC4a6BbFCc2c",
    "poolId": 25,
    "decimals": "1e18",
    "lp0": {
      "address": "0xa2B726B1145A4773F68593CF171187d8EBe4d495",
      "oracle": "pancake",
      "oracleId": "INJ",
      "decimals": "1e18"
    },
    "lp1": {
      "address": "0xbb4CdB9CBd36B01bD1cBaEBF2De08d9173bc095c",
      "oracle": "pancake",
      "oracleId": "WBNB",
      "decimals": "1e18"
    }
  },
  {
    "name": "street-unfi-bnb",
    "address": "0x0fF2D8B1A11195526f42905892bCb29e7b9F338D",
    "poolId": 26,
    "decimals": "1e18",
    "lp0": {
      "address": "0x728C5baC3C3e370E372Fc4671f9ef6916b814d8B",
      "oracle": "pancake",
      "oracleId": "UNFI",
      "decimals": "1e18"
    },
    "lp1": {
      "address": "0xbb4CdB9CBd36B01bD1cBaEBF2De08d9173bc095c",
      "oracle": "pancake",
      "oracleId": "WBNB",
      "decimals": "1e18"
    }
  },
  {
    "name": "street-ltc-bnb",
    "address": "0x8Ea481FE8e35c74355DaF9B5f6b3b69F3c864aFc",
    "poolId": 27,
    "decimals": "1e18",
    "lp0": {
      "address": "0x4338665CBB7B2485A8855A139b75D5e34AB0DB94",
      "oracle": "pancake",
      "oracleId": "LTC",
      "decimals": "1e18"
    },
    "lp1": {
      "address": "0xbb4CdB9CBd36B01bD1cBaEBF2De08d9173bc095c",
      "oracle": "pancake",
      "oracleId": "WBNB",
      "decimals": "1e18"
    }
  },
  {
    "name": "street-alpha-bnb",
    "address": "0x8d27dccB0fb3d6621fA4F4155d719f4AF159286e",
    "poolId": 21,
    "decimals": "1e18",
    "lp0": {
      "address": "0xa1faa113cbE53436Df28FF0aEe54275c13B40975",
      "oracle": "pancake",
      "oracleId": "ALPHA",
      "decimals": "1e18"
    },
    "lp1": {
      "address": "0xbb4CdB9CBd36B01bD1cBaEBF2De08d9173bc095c",
      "oracle": "pancake",
      "oracleId": "WBNB",
      "decimals": "1e18"
    }
  },
  {
    "name": "street-bch-bnb",
    "address": "0xcE7b1Bc3ff9115B64Bf4D6B1549f8339D02762F4",
    "poolId": 16,
    "decimals": "1e18",
    "lp0": {
      "address": "0x8fF795a6F4D97E7887C79beA79aba5cc76444aDf",
      "oracle": "pancake",
      "oracleId": "BCH",
      "decimals": "1e18"
    },
    "lp1": {
      "address": "0xbb4CdB9CBd36B01bD1cBaEBF2De08d9173bc095c",
      "oracle": "pancake",
      "oracleId": "WBNB",
      "decimals": "1e18"
    }
  },
  {
    "name": "street-link-bnb",
    "address": "0x2c92d0390f95477c70cb7B4B92050B0Db5D04a1E",
    "poolId": 17,
    "decimals": "1e18",
    "lp0": {
      "address": "0xF8A0BF9cF54Bb92F17374d9e9A321E6a111a51bD",
      "oracle": "pancake",
      "oracleId": "LINK",
      "decimals": "1e18"
    },
    "lp1": {
      "address": "0xbb4CdB9CBd36B01bD1cBaEBF2De08d9173bc095c",
      "oracle": "pancake",
      "oracleId": "WBNB",
      "decimals": "1e18"
    }
  },
  {
    "name": "street-nar-bnb",
    "address": "0x1389003bcb228586648721A4F6187004dAE01c51",
    "poolId": 18,
    "decimals": "1e18",
    "lp0": {
      "address": "0xA1303E6199b319a891b79685F0537D289af1FC83",
      "oracle": "pancake",
      "oracleId": "NAR",
      "decimals": "1e18"
    },
    "lp1": {
      "address": "0xbb4CdB9CBd36B01bD1cBaEBF2De08d9173bc095c",
      "oracle": "pancake",
      "oracleId": "WBNB",
      "decimals": "1e18"
    }
  },

  {
    "name": "street-drugs-bnb",
    "address": "0x421DF185Ff87bc5f19bd5a90102A51452b70c4A4",
    "poolId": 1,
    "decimals": "1e18",
    "lp0": {
      "address": "0x339550404Ca4d831D12B1b2e4768869997390010",
      "oracle": "pancake",
      "oracleId": "DRUGS",
      "decimals": "1e18"
    },
    "lp1": {
      "address": "0xbb4CdB9CBd36B01bD1cBaEBF2De08d9173bc095c",
      "oracle": "pancake",
      "oracleId": "WBNB",
      "decimals": "1e18"
    }
  },
  {
    "name": "street-thugs-bnb",
    "address": "0x9354caB0F1083135439B23aA6c364329e578F39a",
    "poolId": 2,
    "decimals": "1e18",
    "lp0": {
      "address": "0xE10e9822A5de22F8761919310DDA35CD997d63c0",
      "oracle": "pancake",
      "oracleId": "THUGS",
      "decimals": "1e18"
    },
    "lp1": {
      "address": "0xbb4CdB9CBd36B01bD1cBaEBF2De08d9173bc095c",
      "oracle": "pancake",
      "oracleId": "WBNB",
      "decimals": "1e18"
    }
  },
  {
    "name": "street-cred-bnb",
    "address": "0x9CBE4F200b474a1C33bfFe7c6e531e1D47ECab46",
    "poolId": 9,
    "decimals": "1e18",
    "lp0": {
      "address": "0x571D0B55fe30eb1F6E68e8799F181c46De6B0059",
      "oracle": "pancake",
      "oracleId": "CRED",
      "decimals": "1e18"
    },
    "lp1": {
      "address": "0xbb4CdB9CBd36B01bD1cBaEBF2De08d9173bc095c",
      "oracle": "pancake",
      "oracleId": "WBNB",
      "decimals": "1e18"
    }
  },
  {
    "name": "street-guns-bnb",
    "address": "0xa5e5eeB6b51fa0fDc59915C81d75C83470BFA4f0",
    "poolId": 3,
    "decimals": "1e18",
    "lp0": {
      "address": "0x179983892eC36287f1F342443B671Ba549762241",
      "oracle": "pancake",
      "oracleId": "GUNS",
      "decimals": "1e18"
    },
    "lp1": {
      "address": "0xbb4CdB9CBd36B01bD1cBaEBF2De08d9173bc095c",
      "oracle": "pancake",
      "oracleId": "WBNB",
      "decimals": "1e18"
    }
  },
  {
    "name": "street-busd-bnb",
    "address": "0xf2e4E3F9B58b3eDaC88Ad11D689a23f3119a782D",
    "poolId": 4,
    "decimals": "1e18",
    "lp0": {
      "address": "0xe9e7CEA3DedcA5984780Bafc599bD69ADd087D56",
      "oracle": "pancake",
      "oracleId": "BUSD",
      "decimals": "1e18"
    },
    "lp1": {
      "address": "0xbb4CdB9CBd36B01bD1cBaEBF2De08d9173bc095c",
      "oracle": "pancake",
      "oracleId": "WBNB",
      "decimals": "1e18"
    }
  },
  {
    "name": "street-btc-bnb",
    "address": "0xdFb193940E1317f38e91568fdb05EFE18ee4A3c7",
    "poolId": 5,
    "decimals": "1e18",
    "lp0": {
      "address": "0x7130d2A12B9BCbFAe4f2634d864A1Ee1Ce3Ead9c",
      "oracle": "pancake",
      "oracleId": "BTCB",
      "decimals": "1e18"
    },
    "lp1": {
      "address": "0xbb4CdB9CBd36B01bD1cBaEBF2De08d9173bc095c",
      "oracle": "pancake",
      "oracleId": "WBNB",
      "decimals": "1e18"
    }
  },
  {
    "name": "street-eth-bnb",
    "address": "0x75115C644F9661A761A333Ba0A38e42B1649f143",
    "poolId": 6,
    "decimals": "1e18",
    "lp0": {
      "address": "0x2170Ed0880ac9A755fd29B2688956BD959F933F8",
      "oracle": "pancake",
      "oracleId": "ETH",
      "decimals": "1e18"
    },
    "lp1": {
      "address": "0xbb4CdB9CBd36B01bD1cBaEBF2De08d9173bc095c",
      "oracle": "pancake",
      "oracleId": "WBNB",
      "decimals": "1e18"
    }
  },

  {
    "name": "street-panacakelp-thugs-bnb",
    "address": "0x40257481f09dB2211a3274B34554Bbb00B0a7Fb1",
    "poolId": 7,
    "decimals": "1e18",
    "lp0": {
      "address": "0xE10e9822A5de22F8761919310DDA35CD997d63c0",
      "oracle": "pancake",
      "oracleId": "THUGS",
      "decimals": "1e18"
    },
    "lp1": {
      "address": "0xbb4CdB9CBd36B01bD1cBaEBF2De08d9173bc095c",
      "oracle": "pancake",
      "oracleId": "WBNB",
      "decimals": "1e18"
    }
  },
  {
    "name": "street-narwhallp-thugs-bnb",
    "address": "0x40Ff83ac2890DD5469f5eCa2c17dcAf10ee09957",
    "poolId": 8,
    "decimals": "1e18",
    "lp0": {
      "address": "0xE10e9822A5de22F8761919310DDA35CD997d63c0",
      "oracle": "pancake",
      "oracleId": "THUGS",
      "decimals": "1e18"
    },
    "lp1": {
      "address": "0xbb4CdB9CBd36B01bD1cBaEBF2De08d9173bc095c",
      "oracle": "pancake",
      "oracleId": "WBNB",
      "decimals": "1e18"
    }
  },
  {
    "name": "street-dai-bnb",
    "address": "0xed8Ecb790Be568461d85Cf82C386E51124E46a52",
    "poolId": 10,
    "decimals": "1e18",
    "lp0": {
      "address": "0x1AF3F329e8BE154074D8769D1FFa4eE058B1DBc3",
      "oracle": "pancake",
      "oracleId": "0x1AF3F329e8BE154074D8769D1FFa4eE058B1DBc3_0xbb4CdB9CBd36B01bD1cBaEBF2De08d9173bc095c",
      "decimals": "1e18"
    },
    "lp1": {
      "address": "0xbb4CdB9CBd36B01bD1cBaEBF2De08d9173bc095c",
      "oracle": "pancake",
      "oracleId": "WBNB",
      "decimals": "1e18"
    }
  },
  {
    "name": "street-usdt-bnb",
    "address": "0x0d29724d1834Fc65869812BAe5d63dce8aCB7921",
    "poolId": 11,
    "decimals": "1e18",
    "lp0": {
      "address": "0x55d398326f99059fF775485246999027B3197955",
      "oracle": "pancake",
      "oracleId": "USDT",
      "decimals": "1e18"
    },
    "lp1": {
      "address": "0xbb4CdB9CBd36B01bD1cBaEBF2De08d9173bc095c",
      "oracle": "pancake",
      "oracleId": "WBNB",
      "decimals": "1e18"
    }
  },
  {
    "name": "street-bliq-bnb",
    "address": "0xe835ed82C7d9d018f8F5173EECfBb56f29f38570",
    "poolId": 12,
    "decimals": "1e18",
    "lp0": {
      "address": "0xC97faC34CeB0Bb1B2bdAf3b59ADA378b99111a22",
      "oracle": "pancake",
      "oracleId": "BLIQ",
      "decimals": "1e18"
    },
    "lp1": {
      "address": "0xbb4CdB9CBd36B01bD1cBaEBF2De08d9173bc095c",
      "oracle": "pancake",
      "oracleId": "WBNB",
      "decimals": "1e18"
    }
  },

  {
    "name": "street-eos-bnb",
    "address": "0x44e89861096371246eA8E3e86D97781ea24fBB29",
    "poolId": 13,
    "decimals": "1e18",
    "lp0": {
      "address": "0x56b6fB708fC5732DEC1Afc8D8556423A2EDcCbD6",
      "oracle": "pancake",
      "oracleId": "EOS",
      "decimals": "1e18"
    },
    "lp1": {
      "address": "0xbb4CdB9CBd36B01bD1cBaEBF2De08d9173bc095c",
      "oracle": "pancake",
      "oracleId": "WBNB",
      "decimals": "1e18"
    }
  },
  {
    "name": "street-bifi-bnb",
    "address": "0x223B53b64AA5F87D2De194a15701Fc0bC7474A31",
    "poolId": 14,
    "decimals": "1e18",
    "lp0": {
      "address": "0xCa3F508B8e4Dd382eE878A314789373D80A5190A",
      "oracle": "pancake",
      "oracleId": "BIFI",
      "decimals": "1e18"
    },
    "lp1": {
      "address": "0xbb4CdB9CBd36B01bD1cBaEBF2De08d9173bc095c",
      "oracle": "pancake",
      "oracleId": "WBNB",
      "decimals": "1e18"
    }
  }
]
